benjy/__init__.py
benjy/cli.py
benjy/entities.py
benjy/schema.py
benjy/settings.py
benjy/utilities.py
benjy/version.py
benjy/datatypes/__init__.py
benjy/datatypes/datatypes.py
benjy/drivers/__init__.py
benjy/drivers/main.py
benjy/drivers/python.py
benjy-0.0.1.dist-info/LICENSE
benjy-0.0.1.dist-info/METADATA
benjy-0.0.1.dist-info/WHEEL
benjy-0.0.1.dist-info/entry_points.txt
benjy-0.0.1.dist-info/top_level.txt
benjy-0.0.1.dist-info/RECORD
