Metadata-Version: 2.1
Name: benjy
Version: 0.0.1
Summary: Benjy
Home-page: https://github.com/grai-io/arthur
Author: Grai.io
Author-email: ian@grai.io
License: UNKNOWN
Platform: UNKNOWN
Requires-Python: >=3.6
License-File: LICENSE
Requires-Dist: click
Requires-Dist: pyyaml
Requires-Dist: requests
Requires-Dist: confuse
Requires-Dist: diskcache
Requires-Dist: tqdm
Requires-Dist: networkx
Requires-Dist: pandas
Requires-Dist: visions
